curlew/__init__.py
curlew/core.py
curlew/data.py
curlew/geometry.py
curlew/io.py
curlew/visualise.py
curlew/fields/__init__.py
curlew/fields/analytical.py
curlew/fields/fourier.py
curlew/fields/geoinr.py
curlew/fields/initialisation.py
curlew/fields/siren.py
curlew/geology/SF.py
curlew/geology/__init__.py
curlew/geology/interactions.py
curlew/geology/model.py
curlew/utils/__init__.py
curlew/utils/datascreen.py
curlew-1.0.dist-info/licenses/LICENSE
curlew-1.0.dist-info/METADATA
curlew-1.0.dist-info/WHEEL
curlew-1.0.dist-info/top_level.txt
curlew-1.0.dist-info/RECORD
